scriptz/__init__.py
scriptz/__main__.py
scriptz/__version__.py
scriptz/cli.py
scriptz/logger.py
scriptz/scriptz.ini
scriptz/commands/__init__.py
scriptz/commands/create.py
scriptz/commands/init.py
scriptz/commands/run.py
scriptz/commands/version.py
scriptz/commands/view.py
scriptz/manager/__init__.py
scriptz/manager/config.py
scriptz/manager/environ.py
scriptz/manager/folder.py
scriptz/manager/handler.py
scriptz/manager/manager.py
scriptz/manager/script.py
scriptz-0.0.3.dist-info/LICENSE
scriptz-0.0.3.dist-info/METADATA
scriptz-0.0.3.dist-info/WHEEL
scriptz-0.0.3.dist-info/entry_points.txt
scriptz-0.0.3.dist-info/top_level.txt
scriptz-0.0.3.dist-info/RECORD
